LICENSE
README.md
setup.py
qingping/__init__.py
qingping.egg-info/PKG-INFO
qingping.egg-info/SOURCES.txt
qingping.egg-info/dependency_links.txt
qingping.egg-info/requires.txt
qingping.egg-info/top_level.txt