Metadata-Version: 2.1
Name: qingping
Version: 0.3
Summary: Qingping utilities
Home-page: https://github.com/bitrate16/qingping
Author: bitrate16
Author-email: bitrate16@gmail.com
License: GNU Affero General Public License v3
Classifier: Development Status :: 5 - Production/Stable
Classifier: Intended Audience :: Developers
Classifier: Intended Audience :: End Users/Desktop
Classifier: License :: OSI Approved :: GNU Affero General Public License v3
Classifier: Programming Language :: Python
Classifier: Programming Language :: Python :: 3
Classifier: Programming Language :: Python :: 3 :: Only
License-File: LICENSE
Requires-Dist: pygatt
Requires-Dist: attrs
